pygellermann/__init__.py
pygellermann/_version.py
pygellermann/gellermann.py
pygellermann/gui.py
pygellermann-0.1.0.dist-info/LICENSE
pygellermann-0.1.0.dist-info/METADATA
pygellermann-0.1.0.dist-info/WHEEL
pygellermann-0.1.0.dist-info/entry_points.txt
pygellermann-0.1.0.dist-info/top_level.txt
pygellermann-0.1.0.dist-info/RECORD
