Metadata-Version: 2.1
Name: pygellermann
Version: 0.1.0
Summary: A Python Gellermann series generator
Author-email: Yannick Jadoul <Yannick.Jadoul@mpi.nl>
License: GPL-3.0-or-later
Classifier: Development Status :: 5 - Production/Stable
Classifier: License :: OSI Approved :: GNU General Public License v3 or later (GPLv3+)
Classifier: Operating System :: OS Independent
Classifier: Programming Language :: Python
Classifier: Programming Language :: Python :: 3
Requires-Python: >=3.7
License-File: LICENSE
Requires-Dist: pandas
Requires-Dist: qtpy
Requires-Dist: PyQt6
Requires-Dist: pyqtdarktheme
